{
    "code": 200,
    "msg": "数据请求成功",
    "data": [
        {
            "hot": "109万",
            "index": 1,
            "title": "研二女生车祸致高位截瘫练出麒麟臂",
            "url": "https://s.weibo.com/weibo?q=研二女生车祸致高位截瘫练出麒麟臂"
        },
        {
            "hot": "42万",
            "index": 2,
            "title": "中国反制后加拿大油菜籽价格大跌",
            "url": "https://s.weibo.com/weibo?q=中国反制后加拿大油菜籽价格大跌"
        },
        {
            "hot": "35万",
            "index": 3,
            "title": "这是她她她她她她她她的手",
            "url": "https://s.weibo.com/weibo?q=这是她她她她她她她她的手"
        },
        {
            "hot": "35万",
            "index": 4,
            "title": "vivo X300系列",
            "url": "https://s.weibo.com/weibo?q=vivo X300系列"
        },
        {
            "hot": "35万",
            "index": 5,
            "title": "长期熬夜刷手机脸和身体垮了",
            "url": "https://s.weibo.com/weibo?q=长期熬夜刷手机脸和身体垮了"
        },
        {
            "hot": "35万",
            "index": 6,
            "title": "爸爸看手机婴儿车溜下坡翻车",
            "url": "https://s.weibo.com/weibo?q=爸爸看手机婴儿车溜下坡翻车"
        },
        {
            "hot": "32万",
            "index": 7,
            "title": "丝袜奶茶 真有丝袜",
            "url": "https://s.weibo.com/weibo?q=丝袜奶茶 真有丝袜"
        },
        {
            "hot": "32万",
            "index": 8,
            "title": "成毅德佑全球品牌代言人",
            "url": "https://s.weibo.com/weibo?q=成毅德佑全球品牌代言人"
        },
        {
            "hot": "32万",
            "index": 9,
            "title": "老板说第一次短袖生意做了7个月",
            "url": "https://s.weibo.com/weibo?q=老板说第一次短袖生意做了7个月"
        },
        {
            "hot": "32万",
            "index": 10,
            "title": "洗脸巾残留化学纤维存在安全风险",
            "url": "https://s.weibo.com/weibo?q=洗脸巾残留化学纤维存在安全风险"
        },
        {
            "hot": "31万",
            "index": 11,
            "title": "挨家通报停火的巴勒斯坦记者被枪杀",
            "url": "https://s.weibo.com/weibo?q=挨家通报停火的巴勒斯坦记者被枪杀"
        },
        {
            "hot": "31万",
            "index": 12,
            "title": "心动的信号",
            "url": "https://s.weibo.com/weibo?q=心动的信号"
        },
        {
            "hot": "31万",
            "index": 13,
            "title": "徐娇回应标价1850元马面裙面料争议",
            "url": "https://s.weibo.com/weibo?q=徐娇回应标价1850元马面裙面料争议"
        },
        {
            "hot": "31万",
            "index": 14,
            "title": "14岁女生与家人争吵后跳楼身亡",
            "url": "https://s.weibo.com/weibo?q=14岁女生与家人争吵后跳楼身亡"
        },
        {
            "hot": "31万",
            "index": 15,
            "title": "易烊千玺张天赐经常聚会",
            "url": "https://s.weibo.com/weibo?q=易烊千玺张天赐经常聚会"
        },
        {
            "hot": "27万",
            "index": 16,
            "title": "十年前的招聘要求",
            "url": "https://s.weibo.com/weibo?q=十年前的招聘要求"
        },
        {
            "hot": "24万",
            "index": 17,
            "title": "南方降温",
            "url": "https://s.weibo.com/weibo?q=南方降温"
        },
        {
            "hot": "24万",
            "index": 18,
            "title": "衣服阴干那种臭味怎么除掉",
            "url": "https://s.weibo.com/weibo?q=衣服阴干那种臭味怎么除掉"
        },
        {
            "hot": "21万",
            "index": 19,
            "title": "女将军人设很多却火不起来",
            "url": "https://s.weibo.com/weibo?q=女将军人设很多却火不起来"
        },
        {
            "hot": "18万",
            "index": 20,
            "title": "杨汝晴把王乐晨问懵了",
            "url": "https://s.weibo.com/weibo?q=杨汝晴把王乐晨问懵了"
        },
        {
            "hot": "15万",
            "index": 21,
            "title": "张予曦毕雯珺第二",
            "url": "https://s.weibo.com/weibo?q=张予曦毕雯珺第二"
        },
        {
            "hot": "15万",
            "index": 22,
            "title": "树莓小狗的泪痕",
            "url": "https://s.weibo.com/weibo?q=树莓小狗的泪痕"
        },
        {
            "hot": "14万",
            "index": 23,
            "title": "建议word删除空白页纳入义务教育",
            "url": "https://s.weibo.com/weibo?q=建议word删除空白页纳入义务教育"
        },
        {
            "hot": "14万",
            "index": 24,
            "title": "相恋两年要88.8万彩礼才肯结婚",
            "url": "https://s.weibo.com/weibo?q=相恋两年要88.8万彩礼才肯结婚"
        },
        {
            "hot": "14万",
            "index": 25,
            "title": "曝何炅自带衣服救场内幕",
            "url": "https://s.weibo.com/weibo?q=曝何炅自带衣服救场内幕"
        },
        {
            "hot": "13万",
            "index": 26,
            "title": "儿子考61分全家沸腾下馆子庆祝",
            "url": "https://s.weibo.com/weibo?q=儿子考61分全家沸腾下馆子庆祝"
        },
        {
            "hot": "13万",
            "index": 27,
            "title": "共同构建保障妇女权益的治理格局",
            "url": "https://s.weibo.com/weibo?q=共同构建保障妇女权益的治理格局"
        },
        {
            "hot": "12万",
            "index": 28,
            "title": "黄金",
            "url": "https://s.weibo.com/weibo?q=黄金"
        },
        {
            "hot": "11万",
            "index": 29,
            "title": "建议贴身衣物不要穿黑色的",
            "url": "https://s.weibo.com/weibo?q=建议贴身衣物不要穿黑色的"
        },
        {
            "hot": "11万",
            "index": 30,
            "title": "直击湾芯展",
            "url": "https://s.weibo.com/weibo?q=直击湾芯展"
        },
        {
            "hot": "11万",
            "index": 31,
            "title": "竟然人 居然人",
            "url": "https://s.weibo.com/weibo?q=竟然人 居然人"
        },
        {
            "hot": "10万",
            "index": 32,
            "title": "白鹿要回北京补牙了",
            "url": "https://s.weibo.com/weibo?q=白鹿要回北京补牙了"
        },
        {
            "hot": "10万",
            "index": 33,
            "title": "33训练赛必备科目",
            "url": "https://s.weibo.com/weibo?q=33训练赛必备科目"
        },
        {
            "hot": "10万",
            "index": 34,
            "title": "成毅龚俊罗云熙大男主剧repo",
            "url": "https://s.weibo.com/weibo?q=成毅龚俊罗云熙大男主剧repo"
        },
        {
            "hot": "9万",
            "index": 35,
            "title": "苏新皓 全楼的荣耀",
            "url": "https://s.weibo.com/weibo?q=苏新皓 全楼的荣耀"
        },
        {
            "hot": "9万",
            "index": 36,
            "title": "胡歌可隆品牌代言人",
            "url": "https://s.weibo.com/weibo?q=胡歌可隆品牌代言人"
        },
        {
            "hot": "9万",
            "index": 37,
            "title": "LPL冠军选手聚会",
            "url": "https://s.weibo.com/weibo?q=LPL冠军选手聚会"
        },
        {
            "hot": "8万",
            "index": 38,
            "title": "探访成都小汽车爆燃事发地",
            "url": "https://s.weibo.com/weibo?q=探访成都小汽车爆燃事发地"
        },
        {
            "hot": "8万",
            "index": 39,
            "title": "王楚钦亚锦赛表情包",
            "url": "https://s.weibo.com/weibo?q=王楚钦亚锦赛表情包"
        },
        {
            "hot": "8万",
            "index": 40,
            "title": "男子扶老人被诬耗时十余日自证清白",
            "url": "https://s.weibo.com/weibo?q=男子扶老人被诬耗时十余日自证清白"
        },
        {
            "hot": "8万",
            "index": 41,
            "title": "动脉斑块能有多硬",
            "url": "https://s.weibo.com/weibo?q=动脉斑块能有多硬"
        },
        {
            "hot": "7万",
            "index": 42,
            "title": "你好种地少年3",
            "url": "https://s.weibo.com/weibo?q=你好种地少年3"
        },
        {
            "hot": "7万",
            "index": 43,
            "title": "妇女的手是什么样的",
            "url": "https://s.weibo.com/weibo?q=妇女的手是什么样的"
        },
        {
            "hot": "7万",
            "index": 44,
            "title": "熬夜后多吃这3类食物",
            "url": "https://s.weibo.com/weibo?q=熬夜后多吃这3类食物"
        },
        {
            "hot": "7万",
            "index": 45,
            "title": "这亲家算是门当户对了",
            "url": "https://s.weibo.com/weibo?q=这亲家算是门当户对了"
        },
        {
            "hot": "7万",
            "index": 46,
            "title": "明星AI擦边内容成流量密码",
            "url": "https://s.weibo.com/weibo?q=明星AI擦边内容成流量密码"
        },
        {
            "hot": "7万",
            "index": 47,
            "title": "A股",
            "url": "https://s.weibo.com/weibo?q=A股"
        },
        {
            "hot": "7万",
            "index": 48,
            "title": "辅导员结婚还在回学生消息",
            "url": "https://s.weibo.com/weibo?q=辅导员结婚还在回学生消息"
        },
        {
            "hot": "7万",
            "index": 49,
            "title": "曝JackeyLove与iG三人录节目",
            "url": "https://s.weibo.com/weibo?q=曝JackeyLove与iG三人录节目"
        },
        {
            "hot": "6万",
            "index": 50,
            "title": "鹿晗小卡",
            "url": "https://s.weibo.com/weibo?q=鹿晗小卡"
        },
        {
            "hot": "6万",
            "index": 51,
            "title": "小猫有自己的吃饭仪式感",
            "url": "https://s.weibo.com/weibo?q=小猫有自己的吃饭仪式感"
        },
        {
            "hot": "6万",
            "index": 52,
            "title": "独居最容易面临的心理问题",
            "url": "https://s.weibo.com/weibo?q=独居最容易面临的心理问题"
        }
    ],
    "request_id": "fa87deb2e929f7dde8e49488"
}