{
    "code": 200,
    "msg": "数据请求成功",
    "data": [
        {
            "hot": "115万",
            "index": 1,
            "title": "缅北刘家强迫女性吸毒",
            "url": "https://s.weibo.com/weibo?q=缅北刘家强迫女性吸毒"
        },
        {
            "hot": "60万",
            "index": 2,
            "title": "缅北电诈首富",
            "url": "https://s.weibo.com/weibo?q=缅北电诈首富"
        },
        {
            "hot": "48万",
            "index": 3,
            "title": "中国原子弹爆炸成功61周年",
            "url": "https://s.weibo.com/weibo?q=中国原子弹爆炸成功61周年"
        },
        {
            "hot": "39万",
            "index": 4,
            "title": "刘家电诈园区统一建炮楼",
            "url": "https://s.weibo.com/weibo?q=刘家电诈园区统一建炮楼"
        },
        {
            "hot": "26万",
            "index": 5,
            "title": "女孩经短视频引流治疗后12天去世",
            "url": "https://s.weibo.com/weibo?q=女孩经短视频引流治疗后12天去世"
        },
        {
            "hot": "24万",
            "index": 6,
            "title": "夏静石死在了大仇得报的那一天",
            "url": "https://s.weibo.com/weibo?q=夏静石死在了大仇得报的那一天"
        },
        {
            "hot": "23万",
            "index": 7,
            "title": "印度首富妻子的爱马仕镶了3025颗钻",
            "url": "https://s.weibo.com/weibo?q=印度首富妻子的爱马仕镶了3025颗钻"
        },
        {
            "hot": "17万",
            "index": 8,
            "title": "TheShy回应上单韦鲁斯",
            "url": "https://s.weibo.com/weibo?q=TheShy回应上单韦鲁斯"
        },
        {
            "hot": "16万",
            "index": 9,
            "title": "暗河传OST阵容",
            "url": "https://s.weibo.com/weibo?q=暗河传OST阵容"
        },
        {
            "hot": "15万",
            "index": 10,
            "title": "黄金涨幅52%专家称有短期回调可能",
            "url": "https://s.weibo.com/weibo?q=黄金涨幅52%专家称有短期回调可能"
        },
        {
            "hot": "15万",
            "index": 11,
            "title": "黄子韬徐艺洋婚礼",
            "url": "https://s.weibo.com/weibo?q=黄子韬徐艺洋婚礼"
        },
        {
            "hot": "15万",
            "index": 12,
            "title": "何炅说现在特别痛苦又近视又老花",
            "url": "https://s.weibo.com/weibo?q=何炅说现在特别痛苦又近视又老花"
        },
        {
            "hot": "15万",
            "index": 13,
            "title": "王俊凯几乎零片酬出演刺猬",
            "url": "https://s.weibo.com/weibo?q=王俊凯几乎零片酬出演刺猬"
        },
        {
            "hot": "14万",
            "index": 14,
            "title": "刘宇宁京东直播",
            "url": "https://s.weibo.com/weibo?q=刘宇宁京东直播"
        },
        {
            "hot": "14万",
            "index": 15,
            "title": "研究生自己的4399",
            "url": "https://s.weibo.com/weibo?q=研究生自己的4399"
        },
        {
            "hot": "14万",
            "index": 16,
            "title": "黄子韬 抛西兰花",
            "url": "https://s.weibo.com/weibo?q=黄子韬 抛西兰花"
        },
        {
            "hot": "14万",
            "index": 17,
            "title": "榜一大哥称已正式起诉旺仔小乔",
            "url": "https://s.weibo.com/weibo?q=榜一大哥称已正式起诉旺仔小乔"
        },
        {
            "hot": "14万",
            "index": 18,
            "title": "刘嘉玲被问怎么不生孩子",
            "url": "https://s.weibo.com/weibo?q=刘嘉玲被问怎么不生孩子"
        },
        {
            "hot": "14万",
            "index": 19,
            "title": "六成妈妈因哺乳不便减少外出",
            "url": "https://s.weibo.com/weibo?q=六成妈妈因哺乳不便减少外出"
        },
        {
            "hot": "14万",
            "index": 20,
            "title": "大国粮仓的科技密码",
            "url": "https://s.weibo.com/weibo?q=大国粮仓的科技密码"
        },
        {
            "hot": "14万",
            "index": 21,
            "title": "路行说邓莎最大的付出是生儿子",
            "url": "https://s.weibo.com/weibo?q=路行说邓莎最大的付出是生儿子"
        },
        {
            "hot": "14万",
            "index": 22,
            "title": "怀孕9个月的超模为维密大秀开场",
            "url": "https://s.weibo.com/weibo?q=怀孕9个月的超模为维密大秀开场"
        },
        {
            "hot": "14万",
            "index": 23,
            "title": "有人卖七八公斤金条变现700多万",
            "url": "https://s.weibo.com/weibo?q=有人卖七八公斤金条变现700多万"
        },
        {
            "hot": "14万",
            "index": 24,
            "title": "徐志胜回应和孟子义直播说国粹",
            "url": "https://s.weibo.com/weibo?q=徐志胜回应和孟子义直播说国粹"
        },
        {
            "hot": "14万",
            "index": 25,
            "title": "肖战说永远要真诚",
            "url": "https://s.weibo.com/weibo?q=肖战说永远要真诚"
        },
        {
            "hot": "14万",
            "index": 26,
            "title": "黄奕 地母系长相",
            "url": "https://s.weibo.com/weibo?q=黄奕 地母系长相"
        },
        {
            "hot": "13万",
            "index": 27,
            "title": "KPL选手的王者ID",
            "url": "https://s.weibo.com/weibo?q=KPL选手的王者ID"
        },
        {
            "hot": "13万",
            "index": 28,
            "title": "这居然是高伟光",
            "url": "https://s.weibo.com/weibo?q=这居然是高伟光"
        },
        {
            "hot": "13万",
            "index": 29,
            "title": "奔跑吧特别季阵容",
            "url": "https://s.weibo.com/weibo?q=奔跑吧特别季阵容"
        },
        {
            "hot": "13万",
            "index": 30,
            "title": "再见爱人5开播",
            "url": "https://s.weibo.com/weibo?q=再见爱人5开播"
        },
        {
            "hot": "13万",
            "index": 31,
            "title": "考研人发型",
            "url": "https://s.weibo.com/weibo?q=考研人发型"
        },
        {
            "hot": "13万",
            "index": 32,
            "title": "呼吸道合胞病毒已进入流行期",
            "url": "https://s.weibo.com/weibo?q=呼吸道合胞病毒已进入流行期"
        },
        {
            "hot": "13万",
            "index": 33,
            "title": "林心如霍建华财务各自独立",
            "url": "https://s.weibo.com/weibo?q=林心如霍建华财务各自独立"
        },
        {
            "hot": "13万",
            "index": 34,
            "title": "旺仔小乔掉粉超695万",
            "url": "https://s.weibo.com/weibo?q=旺仔小乔掉粉超695万"
        },
        {
            "hot": "12万",
            "index": 35,
            "title": "我听交警的事件涉事女子被行拘",
            "url": "https://s.weibo.com/weibo?q=我听交警的事件涉事女子被行拘"
        },
        {
            "hot": "12万",
            "index": 36,
            "title": "杨幂维密翅膀",
            "url": "https://s.weibo.com/weibo?q=杨幂维密翅膀"
        },
        {
            "hot": "11万",
            "index": 37,
            "title": "何捷用张馨予泡酸萝卜的缸给鱼坐月子",
            "url": "https://s.weibo.com/weibo?q=何捷用张馨予泡酸萝卜的缸给鱼坐月子"
        },
        {
            "hot": "11万",
            "index": 38,
            "title": "金价疯涨黄金回收商生意火爆",
            "url": "https://s.weibo.com/weibo?q=金价疯涨黄金回收商生意火爆"
        },
        {
            "hot": "11万",
            "index": 39,
            "title": "王俊凯出发参加NBA名人赛路透",
            "url": "https://s.weibo.com/weibo?q=王俊凯出发参加NBA名人赛路透"
        },
        {
            "hot": "10万",
            "index": 40,
            "title": "前男友直播谈与韦雪分手哭了",
            "url": "https://s.weibo.com/weibo?q=前男友直播谈与韦雪分手哭了"
        },
        {
            "hot": "10万",
            "index": 41,
            "title": "网友吐槽喜茶界面太阴间",
            "url": "https://s.weibo.com/weibo?q=网友吐槽喜茶界面太阴间"
        },
        {
            "hot": "10万",
            "index": 42,
            "title": "网友拍到孩子赤裸爬行形似野人",
            "url": "https://s.weibo.com/weibo?q=网友拍到孩子赤裸爬行形似野人"
        },
        {
            "hot": "9万",
            "index": 43,
            "title": "蔚来",
            "url": "https://s.weibo.com/weibo?q=蔚来"
        },
        {
            "hot": "9万",
            "index": 44,
            "title": "市场价165万凶宅26.6万开拍",
            "url": "https://s.weibo.com/weibo?q=市场价165万凶宅26.6万开拍"
        },
        {
            "hot": "9万",
            "index": 45,
            "title": "再见爱人 rapper夫妇",
            "url": "https://s.weibo.com/weibo?q=再见爱人 rapper夫妇"
        },
        {
            "hot": "9万",
            "index": 46,
            "title": "金昭玉醉 暧昧氛围",
            "url": "https://s.weibo.com/weibo?q=金昭玉醉 暧昧氛围"
        },
        {
            "hot": "9万",
            "index": 47,
            "title": "缅北刘家电诈收益全链条覆盖",
            "url": "https://s.weibo.com/weibo?q=缅北刘家电诈收益全链条覆盖"
        },
        {
            "hot": "8万",
            "index": 48,
            "title": "再见爱人",
            "url": "https://s.weibo.com/weibo?q=再见爱人"
        },
        {
            "hot": "8万",
            "index": 49,
            "title": "什么样的人不适合做朋友",
            "url": "https://s.weibo.com/weibo?q=什么样的人不适合做朋友"
        },
        {
            "hot": "8万",
            "index": 50,
            "title": "国考最适合我的岗位是管东北虎",
            "url": "https://s.weibo.com/weibo?q=国考最适合我的岗位是管东北虎"
        }
    ],
    "request_id": "eddc6fa3627bbebaf0fc4d18"
}