{
    "code": 200,
    "msg": "数据请求成功",
    "data": [
        {
            "hot": "109万",
            "index": 1,
            "title": "美国总统叫板美国前总统",
            "url": "https://s.weibo.com/weibo?q=美国总统叫板美国前总统"
        },
        {
            "hot": "24万",
            "index": 2,
            "title": "中方回应朝鲜发射多枚弹道导弹",
            "url": "https://s.weibo.com/weibo?q=中方回应朝鲜发射多枚弹道导弹"
        },
        {
            "hot": "21万",
            "index": 3,
            "title": "这是大国工程的声音",
            "url": "https://s.weibo.com/weibo?q=这是大国工程的声音"
        },
        {
            "hot": "20万",
            "index": 4,
            "title": "原来羽绒服里少穿比多穿更暖和",
            "url": "https://s.weibo.com/weibo?q=原来羽绒服里少穿比多穿更暖和"
        },
        {
            "hot": "19万",
            "index": 5,
            "title": "无畏哭了",
            "url": "https://s.weibo.com/weibo?q=无畏哭了"
        },
        {
            "hot": "18万",
            "index": 6,
            "title": "秋天里的大美中国",
            "url": "https://s.weibo.com/weibo?q=秋天里的大美中国"
        },
        {
            "hot": "18万",
            "index": 7,
            "title": "努比亚Z80 Ultra街拍游戏机",
            "url": "https://s.weibo.com/weibo?q=努比亚Z80 Ultra街拍游戏机"
        },
        {
            "hot": "18万",
            "index": 8,
            "title": "闲鱼回应平台出现卢浮宫珠宝",
            "url": "https://s.weibo.com/weibo?q=闲鱼回应平台出现卢浮宫珠宝"
        },
        {
            "hot": "18万",
            "index": 9,
            "title": "曝VOGUE盛典拖欠劳务费",
            "url": "https://s.weibo.com/weibo?q=曝VOGUE盛典拖欠劳务费"
        },
        {
            "hot": "18万",
            "index": 10,
            "title": "王源演唱会",
            "url": "https://s.weibo.com/weibo?q=王源演唱会"
        },
        {
            "hot": "18万",
            "index": 11,
            "title": "一张图片证明你那里有多冷",
            "url": "https://s.weibo.com/weibo?q=一张图片证明你那里有多冷"
        },
        {
            "hot": "17万",
            "index": 12,
            "title": "月入一万以下最好的理财方式",
            "url": "https://s.weibo.com/weibo?q=月入一万以下最好的理财方式"
        },
        {
            "hot": "17万",
            "index": 13,
            "title": "何赛飞为全场呼唤陈丽君名字激动",
            "url": "https://s.weibo.com/weibo?q=何赛飞为全场呼唤陈丽君名字激动"
        },
        {
            "hot": "17万",
            "index": 14,
            "title": "党的二十届四中全会",
            "url": "https://s.weibo.com/weibo?q=党的二十届四中全会"
        },
        {
            "hot": "17万",
            "index": 15,
            "title": "宠物店起火宠物无一生还",
            "url": "https://s.weibo.com/weibo?q=宠物店起火宠物无一生还"
        },
        {
            "hot": "17万",
            "index": 16,
            "title": "Doinb回应小天",
            "url": "https://s.weibo.com/weibo?q=Doinb回应小天"
        },
        {
            "hot": "17万",
            "index": 17,
            "title": "乌干达发生严重车祸致63死",
            "url": "https://s.weibo.com/weibo?q=乌干达发生严重车祸致63死"
        },
        {
            "hot": "17万",
            "index": 18,
            "title": "小天回应19年FPX兄弟情",
            "url": "https://s.weibo.com/weibo?q=小天回应19年FPX兄弟情"
        },
        {
            "hot": "17万",
            "index": 19,
            "title": "常华森特别出演天地剑心",
            "url": "https://s.weibo.com/weibo?q=常华森特别出演天地剑心"
        },
        {
            "hot": "17万",
            "index": 20,
            "title": "第一次见四平台加央视一起播的剧",
            "url": "https://s.weibo.com/weibo?q=第一次见四平台加央视一起播的剧"
        },
        {
            "hot": "17万",
            "index": 21,
            "title": "龚俊第一部大男主剧",
            "url": "https://s.weibo.com/weibo?q=龚俊第一部大男主剧"
        },
        {
            "hot": "17万",
            "index": 22,
            "title": "牛骏峰闷声干大事",
            "url": "https://s.weibo.com/weibo?q=牛骏峰闷声干大事"
        },
        {
            "hot": "16万",
            "index": 23,
            "title": "金价",
            "url": "https://s.weibo.com/weibo?q=金价"
        },
        {
            "hot": "16万",
            "index": 24,
            "title": "林俊杰jj20世界巡回演唱会",
            "url": "https://s.weibo.com/weibo?q=林俊杰jj20世界巡回演唱会"
        },
        {
            "hot": "16万",
            "index": 25,
            "title": "锦州是真火了",
            "url": "https://s.weibo.com/weibo?q=锦州是真火了"
        },
        {
            "hot": "16万",
            "index": 26,
            "title": "印度总统直升机降落时停机坪塌陷",
            "url": "https://s.weibo.com/weibo?q=印度总统直升机降落时停机坪塌陷"
        },
        {
            "hot": "15万",
            "index": 27,
            "title": "张博恒世锦赛全能银牌",
            "url": "https://s.weibo.com/weibo?q=张博恒世锦赛全能银牌"
        },
        {
            "hot": "15万",
            "index": 28,
            "title": "全球超13万汽车人将失业",
            "url": "https://s.weibo.com/weibo?q=全球超13万汽车人将失业"
        },
        {
            "hot": "15万",
            "index": 29,
            "title": "黄金",
            "url": "https://s.weibo.com/weibo?q=黄金"
        },
        {
            "hot": "15万",
            "index": 30,
            "title": "老外又带更多老外来中国",
            "url": "https://s.weibo.com/weibo?q=老外又带更多老外来中国"
        },
        {
            "hot": "15万",
            "index": 31,
            "title": "10月就穿羽绒服了",
            "url": "https://s.weibo.com/weibo?q=10月就穿羽绒服了"
        },
        {
            "hot": "15万",
            "index": 32,
            "title": "第一眼以为是丑东西切开后惊艳我了",
            "url": "https://s.weibo.com/weibo?q=第一眼以为是丑东西切开后惊艳我了"
        },
        {
            "hot": "15万",
            "index": 33,
            "title": "大乱斗",
            "url": "https://s.weibo.com/weibo?q=大乱斗"
        },
        {
            "hot": "14万",
            "index": 34,
            "title": "星品影响力",
            "url": "https://s.weibo.com/weibo?q=星品影响力"
        },
        {
            "hot": "14万",
            "index": 35,
            "title": "名创优品80%门店将关闭重开",
            "url": "https://s.weibo.com/weibo?q=名创优品80%门店将关闭重开"
        },
        {
            "hot": "14万",
            "index": 36,
            "title": "但凡在吃药就尽量别吃柚子",
            "url": "https://s.weibo.com/weibo?q=但凡在吃药就尽量别吃柚子"
        },
        {
            "hot": "14万",
            "index": 37,
            "title": "年轻人为什么不爱喝养乐多了",
            "url": "https://s.weibo.com/weibo?q=年轻人为什么不爱喝养乐多了"
        },
        {
            "hot": "14万",
            "index": 38,
            "title": "iPhone17Pro的受害者出现了",
            "url": "https://s.weibo.com/weibo?q=iPhone17Pro的受害者出现了"
        },
        {
            "hot": "14万",
            "index": 39,
            "title": "片仔癀十年增长神话终结",
            "url": "https://s.weibo.com/weibo?q=片仔癀十年增长神话终结"
        },
        {
            "hot": "14万",
            "index": 40,
            "title": "又一名32岁男子徒步深圳望郎归遇难",
            "url": "https://s.weibo.com/weibo?q=又一名32岁男子徒步深圳望郎归遇难"
        },
        {
            "hot": "14万",
            "index": 41,
            "title": "第一次感受到藏马熊的恐怖",
            "url": "https://s.weibo.com/weibo?q=第一次感受到藏马熊的恐怖"
        },
        {
            "hot": "14万",
            "index": 42,
            "title": "国务院同意设立全民阅读活动周",
            "url": "https://s.weibo.com/weibo?q=国务院同意设立全民阅读活动周"
        },
        {
            "hot": "14万",
            "index": 43,
            "title": "金价这轮会跌多久",
            "url": "https://s.weibo.com/weibo?q=金价这轮会跌多久"
        },
        {
            "hot": "14万",
            "index": 44,
            "title": "G2战胜FLY",
            "url": "https://s.weibo.com/weibo?q=G2战胜FLY"
        },
        {
            "hot": "14万",
            "index": 45,
            "title": "细腻底妆技巧",
            "url": "https://s.weibo.com/weibo?q=细腻底妆技巧"
        },
        {
            "hot": "14万",
            "index": 46,
            "title": "JDG遗憾止步年总",
            "url": "https://s.weibo.com/weibo?q=JDG遗憾止步年总"
        },
        {
            "hot": "14万",
            "index": 47,
            "title": "S15封面队伍全败",
            "url": "https://s.weibo.com/weibo?q=S15封面队伍全败"
        },
        {
            "hot": "14万",
            "index": 48,
            "title": "冷冷冷我冷冷冷",
            "url": "https://s.weibo.com/weibo?q=冷冷冷我冷冷冷"
        },
        {
            "hot": "14万",
            "index": 49,
            "title": "婴儿车侧翻女子飞扑挽救",
            "url": "https://s.weibo.com/weibo?q=婴儿车侧翻女子飞扑挽救"
        },
        {
            "hot": "14万",
            "index": 50,
            "title": "百人测评团组队为用户验货",
            "url": "https://s.weibo.com/weibo?q=百人测评团组队为用户验货"
        },
        {
            "hot": "14万",
            "index": 51,
            "title": "王俊凯乌镇戏剧节vlog",
            "url": "https://s.weibo.com/weibo?q=王俊凯乌镇戏剧节vlog"
        }
    ],
    "request_id": "4a16ad2589003683376bfe90"
}