{
    "code": 200,
    "msg": "数据请求成功",
    "data": [
        {
            "hot": "106万",
            "index": 1,
            "title": "郑丽文支持者激动落泪说我是中国人",
            "url": "https://s.weibo.com/weibo?q=郑丽文支持者激动落泪说我是中国人"
        },
        {
            "hot": "77万",
            "index": 2,
            "title": "台风风神已进入我国南海",
            "url": "https://s.weibo.com/weibo?q=台风风神已进入我国南海"
        },
        {
            "hot": "63万",
            "index": 3,
            "title": "一张图了解四中全会",
            "url": "https://s.weibo.com/weibo?q=一张图了解四中全会"
        },
        {
            "hot": "60万",
            "index": 4,
            "title": "今晚8点上淘宝用双11万元大券包",
            "url": "https://s.weibo.com/weibo?q=今晚8点上淘宝用双11万元大券包"
        },
        {
            "hot": "59万",
            "index": 5,
            "title": "水龙吟定档",
            "url": "https://s.weibo.com/weibo?q=水龙吟定档"
        },
        {
            "hot": "51万",
            "index": 6,
            "title": "二十届四中全会",
            "url": "https://s.weibo.com/weibo?q=二十届四中全会"
        },
        {
            "hot": "46万",
            "index": 7,
            "title": "卢浮宫8件失窃藏品清单",
            "url": "https://s.weibo.com/weibo?q=卢浮宫8件失窃藏品清单"
        },
        {
            "hot": "46万",
            "index": 8,
            "title": "王安宇的笑容好治愈",
            "url": "https://s.weibo.com/weibo?q=王安宇的笑容好治愈"
        },
        {
            "hot": "45万",
            "index": 9,
            "title": "虽然不能同时拥有一切",
            "url": "https://s.weibo.com/weibo?q=虽然不能同时拥有一切"
        },
        {
            "hot": "44万",
            "index": 10,
            "title": "卢浮宫遭劫已立案调查",
            "url": "https://s.weibo.com/weibo?q=卢浮宫遭劫已立案调查"
        },
        {
            "hot": "43万",
            "index": 11,
            "title": "前三季度中国GDP同比增长5.2%",
            "url": "https://s.weibo.com/weibo?q=前三季度中国GDP同比增长5.2%"
        },
        {
            "hot": "42万",
            "index": 12,
            "title": "iPhone17pro天猫官旗首次降价",
            "url": "https://s.weibo.com/weibo?q=iPhone17pro天猫官旗首次降价"
        },
        {
            "hot": "40万",
            "index": 13,
            "title": "找同学操办婚礼到现场两眼一黑",
            "url": "https://s.weibo.com/weibo?q=找同学操办婚礼到现场两眼一黑"
        },
        {
            "hot": "39万",
            "index": 14,
            "title": "公务员连续旷工超15个工作日被辞退",
            "url": "https://s.weibo.com/weibo?q=公务员连续旷工超15个工作日被辞退"
        },
        {
            "hot": "39万",
            "index": 15,
            "title": "迪丽热巴新剧搭档陈昊森",
            "url": "https://s.weibo.com/weibo?q=迪丽热巴新剧搭档陈昊森"
        },
        {
            "hot": "37万",
            "index": 16,
            "title": "成毅冰雪心动瞬间",
            "url": "https://s.weibo.com/weibo?q=成毅冰雪心动瞬间"
        },
        {
            "hot": "36万",
            "index": 17,
            "title": "礼遇季每小时抽1111元",
            "url": "https://s.weibo.com/weibo?q=礼遇季每小时抽1111元"
        },
        {
            "hot": "36万",
            "index": 18,
            "title": "陈乔恩25包除湿剂买成25箱",
            "url": "https://s.weibo.com/weibo?q=陈乔恩25包除湿剂买成25箱"
        },
        {
            "hot": "34万",
            "index": 19,
            "title": "任嘉伦受伤",
            "url": "https://s.weibo.com/weibo?q=任嘉伦受伤"
        },
        {
            "hot": "29万",
            "index": 20,
            "title": "于正选择周柯宇赵晴的理由",
            "url": "https://s.weibo.com/weibo?q=于正选择周柯宇赵晴的理由"
        },
        {
            "hot": "25万",
            "index": 21,
            "title": "这些人不能乱吃止痛药",
            "url": "https://s.weibo.com/weibo?q=这些人不能乱吃止痛药"
        },
        {
            "hot": "22万",
            "index": 22,
            "title": "头痛睡不着有救了",
            "url": "https://s.weibo.com/weibo?q=头痛睡不着有救了"
        },
        {
            "hot": "22万",
            "index": 23,
            "title": "黄金",
            "url": "https://s.weibo.com/weibo?q=黄金"
        },
        {
            "hot": "22万",
            "index": 24,
            "title": "狗 接完你的接你的",
            "url": "https://s.weibo.com/weibo?q=狗 接完你的接你的"
        },
        {
            "hot": "21万",
            "index": 25,
            "title": "李沁和苏暮雨一起破局",
            "url": "https://s.weibo.com/weibo?q=李沁和苏暮雨一起破局"
        },
        {
            "hot": "20万",
            "index": 26,
            "title": "迪丽热巴大女主排面",
            "url": "https://s.weibo.com/weibo?q=迪丽热巴大女主排面"
        },
        {
            "hot": "19万",
            "index": 27,
            "title": "印媒惊喜美智库把印空军排中国前",
            "url": "https://s.weibo.com/weibo?q=印媒惊喜美智库把印空军排中国前"
        },
        {
            "hot": "19万",
            "index": 28,
            "title": "令人心动的offer",
            "url": "https://s.weibo.com/weibo?q=令人心动的offer"
        },
        {
            "hot": "19万",
            "index": 29,
            "title": "入局阵容官宣",
            "url": "https://s.weibo.com/weibo?q=入局阵容官宣"
        },
        {
            "hot": "19万",
            "index": 30,
            "title": "暗河传开播",
            "url": "https://s.weibo.com/weibo?q=暗河传开播"
        },
        {
            "hot": "19万",
            "index": 31,
            "title": "X剧场首部女性罪案剧",
            "url": "https://s.weibo.com/weibo?q=X剧场首部女性罪案剧"
        },
        {
            "hot": "19万",
            "index": 32,
            "title": "三高人群患带状疱疹风险更高",
            "url": "https://s.weibo.com/weibo?q=三高人群患带状疱疹风险更高"
        },
        {
            "hot": "19万",
            "index": 33,
            "title": "秋冬化妆前的护肤公式",
            "url": "https://s.weibo.com/weibo?q=秋冬化妆前的护肤公式"
        },
        {
            "hot": "17万",
            "index": 34,
            "title": "美智库排名印度空军竟超过中国",
            "url": "https://s.weibo.com/weibo?q=美智库排名印度空军竟超过中国"
        },
        {
            "hot": "17万",
            "index": 35,
            "title": "瘦了26斤的面部折叠度",
            "url": "https://s.weibo.com/weibo?q=瘦了26斤的面部折叠度"
        },
        {
            "hot": "16万",
            "index": 36,
            "title": "焕新极氪7X开启预售",
            "url": "https://s.weibo.com/weibo?q=焕新极氪7X开启预售"
        },
        {
            "hot": "16万",
            "index": 37,
            "title": "奥运冠军丁宁任北京先农坛体校校长",
            "url": "https://s.weibo.com/weibo?q=奥运冠军丁宁任北京先农坛体校校长"
        },
        {
            "hot": "15万",
            "index": 38,
            "title": "行李员工资高我是一点都不羡慕",
            "url": "https://s.weibo.com/weibo?q=行李员工资高我是一点都不羡慕"
        },
        {
            "hot": "15万",
            "index": 39,
            "title": "中国人永远记得黄继光",
            "url": "https://s.weibo.com/weibo?q=中国人永远记得黄继光"
        },
        {
            "hot": "15万",
            "index": 40,
            "title": "网友拍到一拉布拉多开电动车上路",
            "url": "https://s.weibo.com/weibo?q=网友拍到一拉布拉多开电动车上路"
        },
        {
            "hot": "14万",
            "index": 41,
            "title": "为什么美国人要人均两份工",
            "url": "https://s.weibo.com/weibo?q=为什么美国人要人均两份工"
        },
        {
            "hot": "14万",
            "index": 42,
            "title": "排队5小时花65元买一个网红煎饼",
            "url": "https://s.weibo.com/weibo?q=排队5小时花65元买一个网红煎饼"
        },
        {
            "hot": "14万",
            "index": 43,
            "title": "谁跟你在一起都会抑郁的",
            "url": "https://s.weibo.com/weibo?q=谁跟你在一起都会抑郁的"
        },
        {
            "hot": "14万",
            "index": 44,
            "title": "网传千里江山图主演阵容",
            "url": "https://s.weibo.com/weibo?q=网传千里江山图主演阵容"
        },
        {
            "hot": "13万",
            "index": 45,
            "title": "她们不是突然变强只是不再沉默",
            "url": "https://s.weibo.com/weibo?q=她们不是突然变强只是不再沉默"
        },
        {
            "hot": "13万",
            "index": 46,
            "title": "学会给生活脱水后人都轻松了",
            "url": "https://s.weibo.com/weibo?q=学会给生活脱水后人都轻松了"
        },
        {
            "hot": "13万",
            "index": 47,
            "title": "沈腾一盘土豆丝炒了三年",
            "url": "https://s.weibo.com/weibo?q=沈腾一盘土豆丝炒了三年"
        },
        {
            "hot": "12万",
            "index": 48,
            "title": "原来冬天洗澡的时候不能开换气",
            "url": "https://s.weibo.com/weibo?q=原来冬天洗澡的时候不能开换气"
        },
        {
            "hot": "12万",
            "index": 49,
            "title": "抢一张演唱会票被骗17万",
            "url": "https://s.weibo.com/weibo?q=抢一张演唱会票被骗17万"
        },
        {
            "hot": "10万",
            "index": 50,
            "title": "汪苏泷收到老鼠干",
            "url": "https://s.weibo.com/weibo?q=汪苏泷收到老鼠干"
        },
        {
            "hot": "10万",
            "index": 51,
            "title": "一个能让人找到天赋的偏方",
            "url": "https://s.weibo.com/weibo?q=一个能让人找到天赋的偏方"
        },
        {
            "hot": "10万",
            "index": 52,
            "title": "止痛药怎么选才安全",
            "url": "https://s.weibo.com/weibo?q=止痛药怎么选才安全"
        }
    ],
    "request_id": "44df93c5f9908f0715839513"
}